{
  "version": "0.2",
  "language": "en",
  "words": [
    "Fern",
    "automations",
    "Workato",
    "Automations",
    "Balli",
    "productionizing",
    "API",
    "APIs",
    "Credal",
    "copilot",
    "copilots",
    "Kandji",
    "Salesforce",
    "Snowflake",
    "Looker",
    "Jira",
    "Confluence",
    "Zendesk",
    "MongoDB",
    "Firecrawl",
    "Finnhub",
    "Resend",
    "OpenStreetMap",
    "LinkedIn",
    "Workos",
    "Okta",
    "SAML",
    "SCIM",
    "Gsuite",
    "mdx",
    "yml",
    "yaml",
    "config",
    "changelog",
    "readme",
    "sdk",
    "SDKs",
    "SOQL",
    "ITSM",
    "HITL",
    "Jamf",
    "pypi",
    "PYPI",
    "fernapi",
    "pickleball",
    "speadsheet",
    "Preconfigured",
    "Asana",
    "Hubspot",
    "Ashby",
    "performantly",
    "rerank",
    "infosec",
    "Reranking",
    "Nitter",
    "Composio",
    "xoxb",
    "Thambapillai",
    "permissioned",
    "Autoapproved",
    "ACCOUNTADMIN",
    "abcdefg",
    "upsell",
    "HEPA",
    "Agentic",
    "agentic",
    "financials",
    "Financials",
    "buildwithfern",
    "Chatbots"
  ],
  "ignorePaths": [
    "node_modules",
    ".git",
    "dist",
    "build",
    "*.log"
  ],
  "ignoreWords": [
    "blacksmith",
    "vcpu",
    "ubuntu"
  ]
}